{
  "peers": {
    "thor": {
      "talent": 0.5,
      "training": 0.5,
      "temperament": 0.0,
      "interactions": 5212,
      "last_updated": 1772546887.7644749
    },
    "sprout": {
      "talent": 0.5,
      "training": 0.5,
      "temperament": 0.0,
      "interactions": 5210,
      "last_updated": 1772546889.7678568
    },
    "legion": {
      "talent": 0.5,
      "training": 0.5,
      "temperament": 0.0,
      "interactions": 5207,
      "last_updated": 1772546847.515672
    },
    "nomad": {
      "talent": 0.5,
      "training": 0.5,
      "temperament": 0.0,
      "interactions": 5206,
      "last_updated": 1772546849.519325
    },
    "cbp": {
      "talent": 0.5,
      "training": 0.5,
      "temperament": 0.0,
      "interactions": 5206,
      "last_updated": 1772546851.52275
    }
  },
  "last_updated": 1772546889.7682261
}