{
  "track": "training",
  "current_session": 9,
  "current_skill_track": "A",
  "skill_track_progress": {
    "A": {
      "started": "2026-01-10T21:38:33.027378",
      "completed": null,
      "sessions": 9
    },
    "B": {
      "started": null,
      "completed": null,
      "sessions": 0
    },
    "C": {
      "started": null,
      "completed": null,
      "sessions": 0
    },
    "D": {
      "started": null,
      "completed": null,
      "sessions": 0
    }
  },
  "last_session": "2026-01-13T21:01:51.210793",
  "last_session_summary": "T009: 4/5 (80%). Yes/no (water dry?) now answered correctly with 'No'. Completion (cat/mat) marked failed but 'rug' is epistemically valid. Context bleed reduced. Editor framing persists.",
  "skill_observations": [
    "T006-T007 100% streak, T008-T009 at 80% each",
    "Yes/no questions showing recovery (T009 success after T008 failure)",
    "Sentence completion: expects specific word but accepts valid alternatives",
    "Evaluation gap: 'rug' vs 'mat' not a true failure, just different valid answer",
    "Context bleed reduced - final reflection connected to actual exercises",
    "Editor/corrector framing persists but content coherent",
    "Counting improved - spelled numbers with numerals, cleaner structure"
  ],
  "integration_notes": [
    "Primary track: Watch for over-elaboration in conversations",
    "T010 will complete Track A baseline - consider Track B start",
    "Sentence completion exercises may need multiple valid answers in expected",
    "Epistemic validity check important: different ≠ wrong"
  ]
}